stjudecloud_utilities/__init__.py
stjudecloud_utilities/deduplicate_feature_counts.py
stjudecloud_utilities/gtf_to_rseqc_bed.py
stjudecloud_utilities/warden_counts_utils.py
stjudecloud_utilities-1.1.2.dist-info/entry_points.txt
stjudecloud_utilities-1.1.2.dist-info/LICENSE
stjudecloud_utilities-1.1.2.dist-info/WHEEL
stjudecloud_utilities-1.1.2.dist-info/METADATA
stjudecloud_utilities-1.1.2.dist-info/RECORD
